MANIFEST.in
README.rst
setup.py
django_monon.egg-info/PKG-INFO
django_monon.egg-info/SOURCES.txt
django_monon.egg-info/dependency_links.txt
django_monon.egg-info/not-zip-safe
django_monon.egg-info/requires.txt
django_monon.egg-info/top_level.txt
monon/__init__.py
monon/forms/__init__.py
monon/forms/fields.py
monon/forms/widgets.py
monon/models/__init__.py
monon/models/fields.py
monon/models/managers.py
monon/tests/__init__.py
monon/tests/test_fields.py
monon/tests/test_forms.py
monon/tests/dummyapp/__init__.py
monon/tests/dummyapp/forms.py
monon/tests/dummyapp/models.py
monon/tests/dummyapp/settings.py