Metadata-Version: 1.1
Name: django-monon
Version: 0.0.1-dev
Summary: Django fields for use with pymonon
Home-page: https://github.com/pedroburon/django-monon
Author: Pedro Burón
Author-email: pedro@witoi.com
License: UNKNOWN
Platform: UNKNOWN
Classifier: Topic :: Internet :: WWW/HTTP :: Dynamic Content
Classifier: Intended Audience :: Developers
Classifier: Programming Language :: Python
Classifier: Programming Language :: Python :: 2.6
Classifier: Programming Language :: Python :: 2.7
Classifier: Framework :: Django
Classifier: Development Status :: 1 - Planning
Classifier: Operating System :: OS Independent
